subtoaudio/__init__.py
subtoaudio/subtoaudio.py
subtoaudio-0.1.5.dist-info/LICENSE
subtoaudio-0.1.5.dist-info/METADATA
subtoaudio-0.1.5.dist-info/WHEEL
subtoaudio-0.1.5.dist-info/top_level.txt
subtoaudio-0.1.5.dist-info/RECORD
