Metadata-Version: 2.1
Name: subtoaudio
Version: 0.1.5
Summary: Subtitle to Audio, generate audio or speech from any subtitle file
Home-page: https://github.com/bnsantoso/
Author: Bagas NS
Author-email: bagassantoso71@gmail.com
License: MPL 2.0
Keywords: subtitle,tts,text to audio,subtitle to audio,subtitle to speech
Classifier: Development Status :: 4 - Beta
Classifier: Intended Audience :: Developers
Classifier: License :: OSI Approved :: Mozilla Public License 2.0 (MPL 2.0)
Classifier: Programming Language :: Python :: 3.9
License-File: LICENSE
Requires-Dist: pydub
Requires-Dist: librosa
Requires-Dist: ffmpeg-python
